ndtguide/__init__.py
ndtguide/guide.py
ndtguide-0.1.1.dist-info/LICENSE
ndtguide-0.1.1.dist-info/METADATA
ndtguide-0.1.1.dist-info/WHEEL
ndtguide-0.1.1.dist-info/top_level.txt
ndtguide-0.1.1.dist-info/RECORD
