Metadata-Version: 2.1
Name: ndtguide
Version: 0.1.1
Summary: MeasurementLab NDT data query guide
Home-page: https://github.com/bgpkit/ndtguide
Author: Mingwei Zhang
Author-email: mingwei@bgpkit.com
License-File: LICENSE
